gpt_sovits/AR/__init__.py
gpt_sovits/AR/data/__init__.py
gpt_sovits/AR/data/bucket_sampler.py
gpt_sovits/AR/data/data_module.py
gpt_sovits/AR/data/dataset.py
gpt_sovits/AR/models/__init__.py
gpt_sovits/AR/models/t2s_lightning_module.py
gpt_sovits/AR/models/t2s_lightning_module_onnx.py
gpt_sovits/AR/models/t2s_model.py
gpt_sovits/AR/models/t2s_model_onnx.py
gpt_sovits/AR/models/utils.py
gpt_sovits/AR/modules/__init__.py
gpt_sovits/AR/modules/activation.py
gpt_sovits/AR/modules/activation_onnx.py
gpt_sovits/AR/modules/embedding.py
gpt_sovits/AR/modules/embedding_onnx.py
gpt_sovits/AR/modules/lr_schedulers.py
gpt_sovits/AR/modules/optim.py
gpt_sovits/AR/modules/patched_mha_with_cache.py
gpt_sovits/AR/modules/patched_mha_with_cache_onnx.py
gpt_sovits/AR/modules/scaling.py
gpt_sovits/AR/modules/transformer.py
gpt_sovits/AR/modules/transformer_onnx.py
gpt_sovits/AR/text_processing/__init__.py
gpt_sovits/AR/text_processing/phonemizer.py
gpt_sovits/AR/text_processing/symbols.py
gpt_sovits/AR/utils/__init__.py
gpt_sovits/AR/utils/initialize.py
gpt_sovits/AR/utils/io.py
gpt_sovits/__init__.py
gpt_sovits/feature_extractor/__init__.py
gpt_sovits/feature_extractor/cnhubert.py
gpt_sovits/feature_extractor/whisper_enc.py
gpt_sovits/infer/__init__.py
gpt_sovits/infer/inference.py
gpt_sovits/infer/inference_pool.py
gpt_sovits/infer/interface.py
gpt_sovits/infer/text_utils.py
gpt_sovits/module/__init__.py
gpt_sovits/module/attentions.py
gpt_sovits/module/attentions_onnx.py
gpt_sovits/module/commons.py
gpt_sovits/module/core_vq.py
gpt_sovits/module/data_utils.py
gpt_sovits/module/losses.py
gpt_sovits/module/mel_processing.py
gpt_sovits/module/models.py
gpt_sovits/module/models_onnx.py
gpt_sovits/module/modules.py
gpt_sovits/module/mrte_model.py
gpt_sovits/module/quantize.py
gpt_sovits/module/transforms.py
gpt_sovits/my_utils.py
gpt_sovits/onnx_export.py
gpt_sovits/process_ckpt.py
gpt_sovits/s1_train.py
gpt_sovits/s2_train.py
gpt_sovits/text/__init__.py
gpt_sovits/text/chinese.py
gpt_sovits_infer-0.2.8.dist-info/METADATA
gpt_sovits_infer-0.2.8.dist-info/WHEEL
gpt_sovits_infer-0.2.8.dist-info/licenses/LICENSE
gpt_sovits_infer-0.2.8.dist-info/RECORD
