Metadata-Version: 2.1
Name: GPT-SoVITS-Infer
Version: 0.2.8
Summary: Inference code for GPT-SoVITS
Author-Email: Yanli <mail@yanli.one>
License: MIT
Requires-Python: <3.12,>=3.10
Requires-Dist: numpy<2,>=1.26.4
Requires-Dist: scipy>=1.13.1
Requires-Dist: librosa>=0.10.2.post1
Requires-Dist: transformers>=4.41.2
Requires-Dist: LangSegment>=0.3.3
Requires-Dist: einops>=0.8.0
Requires-Dist: matplotlib>=3.9.0
Requires-Dist: cn2an>=0.5.22
Requires-Dist: pypinyin>=0.51.0
Requires-Dist: jieba-fast>=0.53
Requires-Dist: pyopenjtalk>=0.3.3
Requires-Dist: g2p-en>=2.1.0
Requires-Dist: wordsegment>=1.3.1
Requires-Dist: nltk>=3.8.1
Requires-Dist: pydantic>=2.7.4
